{
  "test_date": "2025-12-29",
  "test_type": "dominance_phase_diagram",
  "description": "Dominance sweep across \u0398_lab with normalized slack comparison",
  "br_max": 0.145,
  "use_normalized_slack": true,
  "results": {
    "Theta_lab_1.0": {
      "viable_points": 1500,
      "constraint_dominance": {}
    },
    "Theta_lab_0.3": {
      "viable_points": 1500,
      "constraint_dominance": {}
    },
    "Theta_lab_0.1": {
      "viable_points": 1500,
      "constraint_dominance": {}
    },
    "Theta_lab_0.03": {
      "viable_points": 1500,
      "constraint_dominance": {}
    },
    "Theta_lab_0.01": {
      "viable_points": 1500,
      "constraint_dominance": {}
    },
    "Theta_lab_0.003": {
      "viable_points": 1500,
      "constraint_dominance": {}
    },
    "Theta_lab_0.001": {
      "viable_points": 1500,
      "constraint_dominance": {}
    }
  }
}